dp4plus_app/5069F000
dp4plus_app/HALO_module.py
dp4plus_app/MSTD-Custom-Stand.xlsx
dp4plus_app/MSTD-MM-Stand.xlsx
dp4plus_app/MSTD-QM-Stand.xlsx
dp4plus_app/Qt_threads.py
dp4plus_app/__init__.py
dp4plus_app/bugs_a_warning_module.py
dp4plus_app/correlation_module.py
dp4plus_app/custom_module.py
dp4plus_app/data_base_Custom.xlsx
dp4plus_app/data_base_MM.xlsx
dp4plus_app/data_base_QM.xlsx
dp4plus_app/dp4_module.py
dp4plus_app/main.py
dp4plus_app/output_module.py
dp4plus_app/GUI2/GUI.ui
dp4plus_app/GUI2/HALO_Standard.ui
dp4plus_app/GUI2/HALO_tab.ui
dp4plus_app/GUI2/custom_tab.ui
dp4plus_app/GUI2/custom_trainig_set.ui
dp4plus_app/GUI2/dp4_UG.ui
dp4plus_app/GUI2/dp4_tab.ui
dp4plus_app/GUI2/logo_CONICET.png
dp4plus_app/GUI2/logo_INGEBIO.png
dp4plus_app/GUI2/mm_dp4_tab.ui
dp4plus_app/GUI2/solvent_dialog.ui
dp4plus_app/example_HALO/0 Example Manual - DP4+_HALO.pdf
dp4plus_app/example_HALO/0 UserGuide - DP4+.pdf
dp4plus_app/example_HALO/01_SSSE_Tetrahalogenado_001_nmr.log
dp4plus_app/example_HALO/01_SSSE_Tetrahalogenado_002_nmr.log
dp4plus_app/example_HALO/02_SSSZ_Tetrahalogenado_001_nmr.log
dp4plus_app/example_HALO/02_SSSZ_Tetrahalogenado_002_nmr.log
dp4plus_app/example_HALO/03_SRSE_Tetrahalogenado_001_nmr.log
dp4plus_app/example_HALO/03_SRSE_Tetrahalogenado_002_nmr.log
dp4plus_app/example_HALO/03_SRSE_Tetrahalogenado_003_nmr.log
dp4plus_app/example_HALO/03_SRSE_Tetrahalogenado_004_nmr.log
dp4plus_app/example_HALO/03_SRSE_Tetrahalogenado_005_nmr.log
dp4plus_app/example_HALO/04_SRRE_Tetrahalogenado_001_nmr.log
dp4plus_app/example_HALO/04_SRRE_Tetrahalogenado_002_nmr.log
dp4plus_app/example_HALO/04_SRRE_Tetrahalogenado_003_nmr.log
dp4plus_app/example_HALO/04_SRRE_Tetrahalogenado_004_nmr - brk.log
dp4plus_app/example_HALO/04_SRRE_Tetrahalogenado_004_nmr.log
dp4plus_app/example_HALO/Data_02_SSSZ_Tetragalogenado_app.xlsx
dp4plus_app/example_custom_training/0 Example Manual - Custom.pdf
dp4plus_app/example_custom_training/0 UserGuide - Custom.pdf
dp4plus_app-2.1.3.dist-info/LICENCE
dp4plus_app-2.1.3.dist-info/METADATA
dp4plus_app-2.1.3.dist-info/WHEEL
dp4plus_app-2.1.3.dist-info/entry_points.txt
dp4plus_app-2.1.3.dist-info/top_level.txt
dp4plus_app-2.1.3.dist-info/RECORD
