Metadata-Version: 2.1
Name: dp4plus-app
Version: 2.1.3
Summary: A tool to simplify your DP4+ calculations
Home-page: https://github.com/RosarioCCLab/DP4plus-App
Author: Bruno A. Franco
Author-email: bruno.agustin.franco@gmail.com
License: MIT
Keywords: nmr
Classifier: Programming Language :: Python :: 3
Classifier: License :: OSI Approved :: MIT License
Classifier: Operating System :: OS Independent
Requires-Python: >=3.8
License-File: LICENCE
Requires-Dist: requests
Requires-Dist: numpy
Requires-Dist: openpyxl
Requires-Dist: xlsxwriter
Requires-Dist: pandas
Requires-Dist: pathlib
Requires-Dist: scikit-learn
Requires-Dist: scipy
Requires-Dist: pyqt5
Requires-Dist: Pillow
Requires-Dist: odfpy
Requires-Dist: importlib-metadata ; python_version == "3.8"
